{"_path":"/data/2022/221003soudankai","_dir":"2022","_draft":false,"_partial":false,"_locale":"","title":"デジタルの日(10/3)に「ちいさなデジタル相談室」を浦和の市民活動サポートセンターで開催します。","description":"","date":"2022-10-01","eventDate":"2022-10-03","link":"https://www.facebook.com/events/653216616216053/","thumb":"/images/event221003digital.jpg","body":{"type":"root","children":[],"toc":{"title":"","searchDepth":2,"depth":2,"links":[]}},"_type":"markdown","_id":"content:data:2022:221003soudankai.md","_source":"content","_file":"data/2022/221003soudankai.md","_stem":"data/2022/221003soudankai","_extension":"md"}